data/soccer/app.py
data/soccer/botsort_people_reid.yaml
data/soccer/bytetrack_ball.yaml
engine/__init__.py
engine/device_queue_pool.py
engine/engine_factory.py
engine/engine_manager.py
engine/litert_engine.py
engine/ml_engine.py
engine/onnx_engine.py
engine/openvino_engine.py
engine/pytorch_engine.py
engine/pytorch_vision_engine.py
engine/tensorflow_engine.py
gst_python_ml-1.0.3.dist-info/licenses/COPYING
log/__init__.py
log/global_logger.py
log/gst_logger.py
log/logger.py
log/logger_factory.py
overlay_helper/__init__.py
overlay_helper/overlay_cairo.py
overlay_helper/overlay_opengl.py
overlay_helper/overlay_skia.py
overlay_helper/overlay_utils.py
overlay_helper/overlay_utils_interface.py
overlay_helper/overlay_vulkan.py
utils/__init__.py
utils/analytics_utils.py
utils/caption_utils.py
utils/format_converter.py
utils/gst_feature_manager.py
utils/metadata.py
utils/muxed_buffer_processor.py
utils/runtime_utils.py
gst_python_ml-1.0.3.dist-info/METADATA
gst_python_ml-1.0.3.dist-info/WHEEL
gst_python_ml-1.0.3.dist-info/top_level.txt
gst_python_ml-1.0.3.dist-info/RECORD
