Metadata-Version: 2.4
Name: gst-python-ml
Version: 1.0.3
Summary: An ML package for GStreamer
Author-email: Aaron Boxer <aaron.boxer@collabora.com>
Project-URL: Homepage, https://github.com/collabora/gst-python-ml
Classifier: Programming Language :: Python :: 3
Classifier: License :: OSI Approved :: GNU Lesser General Public License v3 (LGPLv3)
Classifier: Operating System :: OS Independent
Requires-Python: >=3.13
License-File: COPYING
Requires-Dist: pygobject
Requires-Dist: torch==2.9.1
Requires-Dist: torchvision==0.24.1
Requires-Dist: torchaudio==2.9.1
Requires-Dist: transformers==4.56.2
Requires-Dist: qwen-vl-utils[decord]==0.0.8
Requires-Dist: autoawq==0.2.9
Requires-Dist: accelerate==1.12.0
Requires-Dist: bitsandbytes==0.46.1
Requires-Dist: opencv-python==4.10.0.84
Requires-Dist: opencv-contrib-python==4.10.0.84
Requires-Dist: numpy
Requires-Dist: huggingface-hub
Requires-Dist: lap
Requires-Dist: pycairo
Requires-Dist: ultralytics
Requires-Dist: confluent_kafka
Requires-Dist: diffusers
Requires-Dist: sentencepiece
Requires-Dist: protobuf
Requires-Dist: pysilero
Requires-Dist: faster_whisper
Requires-Dist: pysilero-vad
Requires-Dist: whisperspeech
Requires-Dist: webdataset
Requires-Dist: easydict
Requires-Dist: pyflann-py3
Requires-Dist: soundfile
Requires-Dist: speechbrain
Requires-Dist: pyopengl
Provides-Extra: language
Dynamic: license-file
